demo/东百话转北京儿话.dongbei
demo/出溜.dongbei
demo/吃了没老铁.dongbei
demo/增减数值.dongbei
demo/多变量套路.dongbei
demo/套路.dongbei
demo/套路参数.dongbei
demo/字符串.dongbei
demo/导入python模块.dongbei
demo/快速排序.dongbei
demo/数学作业.dongbei
demo/整除和各种套路.dongbei
demo/文斗.dongbei
demo/斐波那契.dongbei
demo/最高指示.dongbei
demo/比较.dongbei
demo/汉诺塔.dongbei
demo/汉诺塔动唤.dongbei
demo/活着.dongbei
demo/活雷锋.dongbei
demo/磨叽.dongbei
demo/算术.dongbei
demo/群众.dongbei
demo/自推套路.dongbei
demo/语法高亮.dongbei
demo/输入.dongbei
demo/阶级.dongbei
src/__init__.py
src/dongbei.dongbei
src/dongbei.py
dongbei_lang-0.0.16.dist-info/LICENSE
dongbei_lang-0.0.16.dist-info/METADATA
dongbei_lang-0.0.16.dist-info/WHEEL
dongbei_lang-0.0.16.dist-info/entry_points.txt
dongbei_lang-0.0.16.dist-info/top_level.txt
dongbei_lang-0.0.16.dist-info/RECORD
