Metadata-Version: 2.1
Name: dongbei-lang
Version: 0.0.16
Summary: Programming language based on Dongbei dialect
Home-page: https://github.com/zhanyong-wan/dongbei
Author: Zhanyong Wan and individual contributors
Author-email: zhanyong-wan@github.com
Project-URL: Dongbei source, https://github.com/zhanyong-wan/dongbei
Classifier: Intended Audience :: Developers
Classifier: License :: OSI Approved :: MIT License
Classifier: Natural Language :: English
Classifier: Operating System :: MacOS :: MacOS X
Classifier: Operating System :: POSIX
Classifier: Operating System :: POSIX :: BSD
Classifier: Operating System :: POSIX :: Linux
Classifier: Operating System :: Microsoft :: Windows
Classifier: Programming Language :: Python
Classifier: Programming Language :: Python :: 3
Classifier: Programming Language :: Python :: 3 :: Only
Classifier: Programming Language :: Python :: 3.6
Classifier: Programming Language :: Python :: 3.7
Classifier: Programming Language :: Python :: 3.8
Requires-Python: >=3.6
License-File: LICENSE
Requires-Dist: setuptools (>=0.7.0)
Requires-Dist: absl-py (>=1.0.0)
